webtable
