Metadata-Version: 2.1
Name: WebTable
Version: 0.11
Summary: get cleaner tables from url or html
Home-page: UNKNOWN
Author: SayaGugu
Author-email: 2708475759@qq.com
License: GPLv3
Platform: UNKNOWN
Requires: pandas
Requires: requests
Requires: opencc
Requires: openpyxl
Requires: selenium
Requires: pyppeteer
Requires: asyncio
